pyhtmltext/__init__.py
pyhtmltext/const.py
pyhtmltext/extractor.py
pyhtmltext/html_parser.py
pyhtmltext-0.1.dist-info/LICENSE.md
pyhtmltext-0.1.dist-info/METADATA
pyhtmltext-0.1.dist-info/WHEEL
pyhtmltext-0.1.dist-info/top_level.txt
pyhtmltext-0.1.dist-info/RECORD
