Metadata-Version: 2.1
Name: pyhtmltext
Version: 0.1
Summary: Usefull tool for extracting text and sentences from html
Home-page: https://github.com/MaksimJames/pyhtmltext
Author: Maksim Prilepsky
Author-email: maksimprilepsky@yandex.ru
Classifier: Programming Language :: Python :: 3
Classifier: License :: OSI Approved :: MIT License
Classifier: Operating System :: OS Independent
Requires-Python: >=3.6
License-File: LICENSE.md
Requires-Dist: razdel (==0.5.0)
